{
  "apiVersion": "v1",
  "kind": "Namespace",
  "metadata": {
    "creationTimestamp": "2022-10-12T07:10:03Z",
    "deletionTimestamp": "2022-10-12T16:35:05Z",
    "labels": {
      "app.kubernetes.io/instance": "flux-system",
      "app.kubernetes.io/part-of": "flux",
      "app.kubernetes.io/version": "v0.28.2",
      "kubernetes.io/metadata.name": "flux-system",
      "pod-security.kubernetes.io/warn": "restricted",
      "pod-security.kubernetes.io/warn-version": "latest"
    },
    "name": "flux-system",
    "resourceVersion": "87653",
    "uid": "3361f8dc-2a75-4d48-9c69-cd2548db0c19"
  },
  "spec": {
    "finalizers": []
  },
  "status": {
    "conditions": [
      {
        "lastTransitionTime": "2022-10-12T16:35:10Z",
        "message": "Discovery failed for some groups, 1 failing: unable to retrieve the complete list of server APIs: metrics.k8s.io/v1beta1: the server is currently unable to handle the request",
        "reason": "DiscoveryFailed",
        "status": "True",
        "type": "NamespaceDeletionDiscoveryFailure"
      },
      {
        "lastTransitionTime": "2022-10-12T16:35:11Z",
        "message": "All legacy kube types successfully parsed",
        "reason": "ParsedGroupVersions",
        "status": "False",
        "type": "NamespaceDeletionGroupVersionParsingFailure"
      },
      {
        "lastTransitionTime": "2022-10-12T16:35:19Z",
        "message": "All content successfully deleted, may be waiting on finalization",
        "reason": "ContentDeleted",
        "status": "False",
        "type": "NamespaceDeletionContentFailure"
      },
      {
        "lastTransitionTime": "2022-10-12T16:35:19Z",
        "message": "All content successfully removed",
        "reason": "ContentRemoved",
        "status": "False",
        "type": "NamespaceContentRemaining"
      },
      {
        "lastTransitionTime": "2022-10-12T16:35:11Z",
        "message": "All content-preserving finalizers finished",
        "reason": "ContentHasNoFinalizers",
        "status": "False",
        "type": "NamespaceFinalizersRemaining"
      }
    ],
    "phase": "Terminating"
  }
}
